inline_snapshot_pandas/__init__.py
inline_snapshot_pandas-0.1.1.dist-info/METADATA
inline_snapshot_pandas-0.1.1.dist-info/WHEEL
inline_snapshot_pandas-0.1.1.dist-info/RECORD
