Metadata-Version: 2.3
Name: inline-snapshot-pandas
Version: 0.1.1
Summary: pandas integration for inline-snapshot (insider only)
Project-URL: Documentation, https://github.com/15r10nk/inline-snapshot-pandas#readme
Project-URL: Issues, https://github.com/15r10nk/inline-snapshot-pandas/issues
Project-URL: Source, https://github.com/15r10nk/inline-snapshot-pandas
Author-email: Frank Hoffmann <15r10nk@polarbit.de>
License-Expression: MIT
Classifier: Development Status :: 4 - Beta
Classifier: Programming Language :: Python
Classifier: Programming Language :: Python :: 3.8
Classifier: Programming Language :: Python :: 3.9
Classifier: Programming Language :: Python :: 3.10
Classifier: Programming Language :: Python :: 3.11
Classifier: Programming Language :: Python :: 3.12
Classifier: Programming Language :: Python :: Implementation :: CPython
Classifier: Programming Language :: Python :: Implementation :: PyPy
Requires-Python: >=3.8
Requires-Dist: inline-snapshot>=0.12.0
Requires-Dist: pandas
